CHANGES.rst
MANIFEST.in
README.rst
requirements-dev.txt
requirements.txt
setup.py
oe_daemonutils/__init__.py
oe_daemonutils/circuit.py
oe_daemonutils/controller.py
oe_daemonutils/notifier.py
oe_daemonutils/processor.py
oe_daemonutils.egg-info/PKG-INFO
oe_daemonutils.egg-info/SOURCES.txt
oe_daemonutils.egg-info/dependency_links.txt
oe_daemonutils.egg-info/entry_points.txt
oe_daemonutils.egg-info/requires.txt
oe_daemonutils.egg-info/top_level.txt
oe_daemonutils/data/__init__.py
oe_daemonutils/data/data_managers.py
oe_daemonutils/data/engine.py
oe_daemonutils/dossierservice/__init__.py
oe_daemonutils/dossierservice/utils.py
oe_daemonutils/dossierservice/commands/__init__.py
oe_daemonutils/dossierservice/commands/actoren/__init__.py
oe_daemonutils/dossierservice/commands/data/__init__.py
oe_daemonutils/dossierservice/commands/location/__init__.py
oe_daemonutils/dossierservice/commands/security/__init__.py