Metadata-Version: 1.1
Name: oe-daemonutils
Version: 0.9.1
Summary: Daemon Utility Library
Home-page: https://github.com/OnroerendErfgoed/oe_daemonutils
Author: Flanders Heritage Agency
Author-email: ict@onroerenderfgoed.be
License: MIT
Keywords: oe daemon utility
Platform: UNKNOWN
Classifier: Development Status :: 3 - Alpha
Classifier: Intended Audience :: Developers
Classifier: Topic :: Utilities
Classifier: License :: OSI Approved :: MIT License
Classifier: Programming Language :: Python :: 2
Classifier: Programming Language :: Python :: 2.7
Classifier: Programming Language :: Python :: 3
Classifier: Programming Language :: Python :: 3.3
Classifier: Programming Language :: Python :: 3.4
